marshmallow_sqlalchemy/__init__.py
marshmallow_sqlalchemy/convert.py
marshmallow_sqlalchemy/exceptions.py
marshmallow_sqlalchemy/fields.py
marshmallow_sqlalchemy/load_instance_mixin.py
marshmallow_sqlalchemy/py.typed
marshmallow_sqlalchemy/schema.py
marshmallow_sqlalchemy-0.30.0.dist-info/AUTHORS.rst
marshmallow_sqlalchemy-0.30.0.dist-info/LICENSE
marshmallow_sqlalchemy-0.30.0.dist-info/METADATA
marshmallow_sqlalchemy-0.30.0.dist-info/WHEEL
marshmallow_sqlalchemy-0.30.0.dist-info/top_level.txt
marshmallow_sqlalchemy-0.30.0.dist-info/RECORD
