Metadata-Version: 2.1
Name: marshmallow-sqlalchemy
Version: 0.30.0
Summary: SQLAlchemy integration with the marshmallow (de)serialization library
Home-page: https://github.com/marshmallow-code/marshmallow-sqlalchemy
Author: Steven Loria
Author-email: sloria1@gmail.com
License: MIT
Project-URL: Changelog, https://marshmallow-sqlalchemy.readthedocs.io/en/latest/changelog.html
Project-URL: Issues, https://github.com/marshmallow-code/marshmallow-sqlalchemy/issues
Project-URL: Funding, https://opencollective.com/marshmallow
Keywords: sqlalchemy marshmallow
Classifier: Intended Audience :: Developers
Classifier: License :: OSI Approved :: MIT License
Classifier: Natural Language :: English
Classifier: Programming Language :: Python :: 3.8
Classifier: Programming Language :: Python :: 3.9
Classifier: Programming Language :: Python :: 3.10
Classifier: Programming Language :: Python :: 3.11
Requires-Python: >=3.8
License-File: LICENSE
License-File: AUTHORS.rst
Requires-Dist: marshmallow>=3.0.0
Requires-Dist: SQLAlchemy<3.0,>=1.4.40
Requires-Dist: packaging>=21.3
Provides-Extra: tests
Requires-Dist: pytest; extra == "tests"
Requires-Dist: pytest-lazy-fixture>=0.6.2; extra == "tests"
Provides-Extra: lint
Requires-Dist: flake8==7.0.0; extra == "lint"
Requires-Dist: flake8-bugbear==23.12.2; extra == "lint"
Requires-Dist: pre-commit==3.6.0; extra == "lint"
Provides-Extra: docs
Requires-Dist: sphinx==7.2.6; extra == "docs"
Requires-Dist: alabaster==0.7.13; extra == "docs"
Requires-Dist: sphinx-issues==3.0.1; extra == "docs"
Provides-Extra: dev
Requires-Dist: pytest; extra == "dev"
Requires-Dist: pytest-lazy-fixture>=0.6.2; extra == "dev"
Requires-Dist: flake8==7.0.0; extra == "dev"
Requires-Dist: flake8-bugbear==23.12.2; extra == "dev"
Requires-Dist: pre-commit==3.6.0; extra == "dev"
Requires-Dist: tox; extra == "dev"
